parssource/__init__.py
parssource/apis.py
parssource/async_sync.py
parssource-0.1.dist-info/METADATA
parssource-0.1.dist-info/WHEEL
parssource-0.1.dist-info/top_level.txt
parssource-0.1.dist-info/RECORD
