Metadata-Version: 2.4
Name: ParsSource
Version: 0.1
Summary: the library SPlus platform for bots.
Home-page: https://github.com/OandONE/SPlus
Author: seyyed mohamad hosein moosavi raja(01)
Author-email: mohamadhosein159159@gmail.com
License: MIT
Requires-Python: >=3.8
Requires-Dist: httpx
Dynamic: author
Dynamic: author-email
Dynamic: description
Dynamic: description-content-type
Dynamic: home-page
Dynamic: license
Dynamic: requires-dist
Dynamic: requires-python
Dynamic: summary
